MANIFEST.in
setup.cfg
setup.py
glb/__init__.py
glb/__main__.py
glb/command.py
glb/settings.py
glb/sockethandler.py
glb.egg-info/PKG-INFO
glb.egg-info/SOURCES.txt
glb.egg-info/dependency_links.txt
glb.egg-info/entry_points.txt
glb.egg-info/not-zip-safe
glb.egg-info/requires.txt
glb.egg-info/top_level.txt
glb/core/__init__.py
glb/core/db.py
glb/core/errors.py
glb/core/extensions.py
glb/haproxy/__init__.py
glb/haproxy/haproxy.py
glb/haproxy/parser.py
glb/haproxy/templates/__haproxy.jinja2
glb/haproxy/templates/haproxy.cfg.jinja2
glb/haproxy/templates/site.jinja2
glb/models/__init__.py
glb/models/balancer.py
glb/models/base.py
glb/models/slave.py
glb/nginx/__init__.py
glb/nginx/nginx.py
glb/nginx/parser.py
glb/nginx/templates/__nginx.jinja2
glb/nginx/templates/http.conf.jinja2
glb/nginx/templates/proxy_params.jinja2
glb/nginx/templates/tcp.conf.jinja2
glb/v1/__init__.py
glb/v1/routes.py
glb/v1/schemas.py
glb/v1/validators.py
glb/v1/api/__init__.py
glb/v1/api/balancer.py
glb/v1/api/balancer_balancer_name.py
glb/v1/api/balancer_balancer_name_backends.py
glb/v1/api/balancer_balancer_name_entrypoints.py
glb/v1/api/balancer_balancer_name_frontend.py
glb/v1/api/balancer_names_postfix.py
glb/v1/api/domain_mappings.py
glb/v1/api/domain_mappings_flush_all.py
glb/v1/api/slaves.py