Metadata-Version: 1.1
Name: glb
Version: 0.0.54
Summary: Guokr load balancing.
Home-page: https://pypi.python.org/pypi/glb/
Author: Aliao
Author-email: aliao0019@gmail.com
License: UNKNOWN
Platform: UNKNOWN
Classifier: Development Status :: 3 - Alpha
Classifier: License :: OSI Approved :: MIT License
Classifier: Programming Language :: Python :: 2.7
